chronometer.py
chronometer-1.0.dist-info/DESCRIPTION.rst
chronometer-1.0.dist-info/zip-safe
chronometer-1.0.dist-info/metadata.json
chronometer-1.0.dist-info/METADATA
chronometer-1.0.dist-info/WHEEL
chronometer-1.0.dist-info/RECORD
chronometer-1.0.dist-info/top_level.txt
